chatbot_tracer-0.8.0.dist-info/licenses/LICENSE
tracer/__init__.py
tracer/agent.py
tracer/constants.py
tracer/main.py
tracer/analysis/__init__.py
tracer/analysis/chatbot_classification.py
tracer/analysis/functionality_extraction.py
tracer/analysis/functionality_refinement.py
tracer/analysis/workflow_builder.py
tracer/conversation/__init__.py
tracer/conversation/conversation_utils.py
tracer/conversation/fallback_detection.py
tracer/conversation/language_detection.py
tracer/conversation/rate_limiter.py
tracer/conversation/session.py
tracer/generation/__init__.py
tracer/generation/context_generation.py
tracer/generation/output_generation.py
tracer/generation/profile_builder.py
tracer/generation/profile_generation.py
tracer/generation/variable/__init__.py
tracer/generation/variable/variable_definition_core.py
tracer/generation/variable/variable_definition_main.py
tracer/generation/variable/variable_matching.py
tracer/generation/variable/variable_parameter_extraction.py
tracer/generation/variable/variable_smart_defaults.py
tracer/generation/variable/variable_validation.py
tracer/graphs/__init__.py
tracer/graphs/profile_graph.py
tracer/graphs/structure_graph.py
tracer/nodes/__init__.py
tracer/nodes/conversation_params_node.py
tracer/nodes/profile_builder_node.py
tracer/nodes/profile_generator_node.py
tracer/nodes/profile_validator_node.py
tracer/nodes/workflow_builder_node.py
tracer/prompts/__init__.py
tracer/prompts/classification_prompts.py
tracer/prompts/context_generation_prompts.py
tracer/prompts/conversation_params_prompts.py
tracer/prompts/fallback_detection_prompts.py
tracer/prompts/functionality_extraction_prompts.py
tracer/prompts/functionality_refinement_prompts.py
tracer/prompts/language_detection_prompts.py
tracer/prompts/output_generation_prompts.py
tracer/prompts/profile_builder_prompts.py
tracer/prompts/profile_generation_prompts.py
tracer/prompts/session_prompts.py
tracer/prompts/variable_definition_prompts.py
tracer/prompts/variable_smart_defaults_prompts.py
tracer/prompts/workflow_prompts.py
chatbot_tracer-0.8.0.dist-info/METADATA
chatbot_tracer-0.8.0.dist-info/WHEEL
chatbot_tracer-0.8.0.dist-info/entry_points.txt
chatbot_tracer-0.8.0.dist-info/top_level.txt
chatbot_tracer-0.8.0.dist-info/RECORD
