Metadata-Version: 2.4
Name: chatbot-tracer
Version: 0.8.0
Summary: A tool to model chatbots and create profiles to test them.
Author-email: Iván Sotillo <ivan.delhorno@uam.es>
License-Expression: GPL-3.0-or-later
Project-URL: Homepage, https://github.com/Chatbot-TRACER/TRACER
Project-URL: Repository, https://github.com/Chatbot-TRACER/TRACER
Project-URL: Issues, https://github.com/Chatbot-TRACER/TRACER/issues
Keywords: chatbot,testing,automation,ai
Classifier: Development Status :: 3 - Alpha
Classifier: Intended Audience :: Developers
Classifier: Natural Language :: English
Classifier: Programming Language :: Python :: 3
Classifier: Programming Language :: Python :: 3.11
Classifier: Programming Language :: Python :: 3.12
Classifier: Topic :: Software Development :: Testing
Requires-Python: >=3.11
License-File: LICENSE
Requires-Dist: bs4>=0.0.2
Requires-Dist: chatbot-connectors==0.6
Requires-Dist: colorama>=0.4.6
Requires-Dist: google-generativeai>=0.8.5
Requires-Dist: graphviz>=0.20.3
Requires-Dist: langchain>=0.3.27
Requires-Dist: langchain-core>=0.3.60
Requires-Dist: langchain-google-genai>=2.0.10
Requires-Dist: langchain-openai>=0.3.17
Requires-Dist: langgraph>=0.4.5
Provides-Extra: dev
Requires-Dist: ruff>=0.1.0; extra == "dev"
Dynamic: license-file
